skeletonizer/__init__.py
skeletonizer/_version.py
skeletonizer/network.py
skeletonizer/skeletonizer.py
skeletonizer-0.0.1.dev1.dist-info/DESCRIPTION.rst
skeletonizer-0.0.1.dev1.dist-info/LICENSE.txt
skeletonizer-0.0.1.dev1.dist-info/METADATA
skeletonizer-0.0.1.dev1.dist-info/RECORD
skeletonizer-0.0.1.dev1.dist-info/WHEEL
skeletonizer-0.0.1.dev1.dist-info/metadata.json
skeletonizer-0.0.1.dev1.dist-info/top_level.txt
