Metadata-Version: 2.0
Name: skeletonizer
Version: 0.0.1.dev1
Summary: Hydraulic network skeletonizer
Home-page: https://gitlab.com/deltares/skeletonizer/
Author: Tjerk Vreeken
Author-email: UNKNOWN
License: UNKNOWN
Download-URL: https://gitlab.com/deltares/skeletonizer/
Platform: Windows
Platform: Linux
Platform: Mac OS-X
Platform: Unix
Classifier: Development Status :: 4 - Beta
Classifier: Intended Audience :: Science/Research
Classifier: Intended Audience :: Information Technology
Classifier: License :: OSI Approved :: GNU Lesser General Public License v3 (LGPLv3)
Classifier: Programming Language :: Python
Classifier: Programming Language :: Python :: 3
Classifier: Topic :: Scientific/Engineering :: GIS
Classifier: Topic :: Scientific/Engineering :: Mathematics
Classifier: Topic :: Scientific/Engineering :: Physics
Classifier: Operating System :: Microsoft :: Windows
Classifier: Operating System :: POSIX
Classifier: Operating System :: Unix
Classifier: Operating System :: MacOS
Requires-Python: >=3.5
